PyTexturePacker/ImageRect.py
PyTexturePacker/Packer.py
PyTexturePacker/Rect.py
PyTexturePacker/Utils.py
PyTexturePacker/__init__.py
PyTexturePacker/GuillotinePacker/GuillotineAtlas.py
PyTexturePacker/GuillotinePacker/GuillotinePacker.py
PyTexturePacker/GuillotinePacker/__init__.py
PyTexturePacker/MaxRectsPacker/MaxRectsAtlas.py
PyTexturePacker/MaxRectsPacker/MaxRectsPacker.py
PyTexturePacker/MaxRectsPacker/__init__.py
PyTexturePacker/PackerInterface/AtlasInterface.py
PyTexturePacker/PackerInterface/PackerInterface.py
PyTexturePacker/PackerInterface/__init__.py
pytexturepacker_xxl-0.1.7.dist-info/METADATA
pytexturepacker_xxl-0.1.7.dist-info/WHEEL
pytexturepacker_xxl-0.1.7.dist-info/licenses/LICENSE.txt
pytexturepacker_xxl-0.1.7.dist-info/RECORD
