Metadata-Version: 2.4
Name: pytexturepacker-xxl
Version: 0.1.7
Summary: 对PyTexturePacker做一个小的扩展
Project-URL: Homepage, https://github.com/lyonDan/PyTexturePacker
Project-URL: Repository, https://github.com/lyonDan/PyTexturePacker
Author-email: Quanyong Huang <quanyongh@foxmail.com>, lyonDan <liangdan6690@gmail.com>
License-Expression: MIT
License-File: LICENSE.txt
Keywords: TexturePacker,cocos2d-x,sprite-sheet,texture-pack
Classifier: License :: OSI Approved :: MIT License
Classifier: Operating System :: OS Independent
Classifier: Programming Language :: Python :: 3
Classifier: Programming Language :: Python :: 3.13
Classifier: Topic :: Multimedia :: Graphics
Requires-Python: >=3.7
Requires-Dist: pillow>=11.3.0
